<?xml version="1.0" encoding="windows-1252"?>
<XMI xmi.version="1.1" xmlns:UML="omg.org/UML1.3">
	<XMI.header>
		<XMI.documentation>
			<XMI.exporter>Enterprise Architect</XMI.exporter>
			<XMI.exporterVersion>2.5</XMI.exporterVersion>
		</XMI.documentation>
	</XMI.header>
	<XMI.content>
		<UML:Model name="EA Model" xmi.id="MX_EAID_6023FBC6_3BDD_4581_9AD7_EB479F476FBB">
			<UML:Namespace.ownedElement>
				<UML:Class name="EARootClass" xmi.id="EAID_11111111_5487_4080_A7F4_41526CB0AA00" isRoot="true" isLeaf="false" isAbstract="false"/>
				<UML:Package name="UC2C.10: Navigate to destination" xmi.id="EAPK_6023FBC6_3BDD_4581_9AD7_EB479F476FBB" isRoot="false" isLeaf="false" isAbstract="false" visibility="public">
					<UML:ModelElement.taggedValue>
						<UML:TaggedValue tag="parent" value="EAPK_CA1BE43D_9336_4df5_A22A_763CA271100D"/>
						<UML:TaggedValue tag="created" value="2012-04-16 17:01:33"/>
						<UML:TaggedValue tag="modified" value="2012-06-04 13:25:47"/>
						<UML:TaggedValue tag="iscontrolled" value="TRUE"/>
						<UML:TaggedValue tag="xmlpath" value="Navigate to destination.xml"/>
						<UML:TaggedValue tag="lastloaddate" value="2012-05-18 16:51:09"/>
						<UML:TaggedValue tag="lastsavedate" value="2012-04-16 18:01:25"/>
						<UML:TaggedValue tag="version" value="1.0"/>
						<UML:TaggedValue tag="isprotected" value="FALSE"/>
						<UML:TaggedValue tag="usedtd" value="FALSE"/>
						<UML:TaggedValue tag="xmiver" value="Enterprise Architect XMI/UML 1.3"/>
						<UML:TaggedValue tag="logxml" value="FALSE"/>
						<UML:TaggedValue tag="tpos" value="0"/>
						<UML:TaggedValue tag="packageFlags" value="Recurse=0;VCCFG=SVN_IM;CRC=0;"/>
						<UML:TaggedValue tag="batchsave" value="0"/>
						<UML:TaggedValue tag="batchload" value="0"/>
						<UML:TaggedValue tag="phase" value="1.0"/>
						<UML:TaggedValue tag="status" value="Proposed"/>
						<UML:TaggedValue tag="author" value="Andrea Bragagnini"/>
						<UML:TaggedValue tag="complexity" value="1"/>
						<UML:TaggedValue tag="ea_stype" value="Public"/>
						<UML:TaggedValue tag="tpos" value="0"/>
						<UML:TaggedValue tag="gentype" value="Java"/>
					</UML:ModelElement.taggedValue>
					<UML:Namespace.ownedElement>
						<UML:Collaboration xmi.id="EAID_6023FBC6_3BDD_4581_9AD7_EB479F476FBB_Collaboration" name="Collaborations">
							<UML:Namespace.ownedElement>
								<UML:ClassifierRole xmi.id="EAID_1DEBE519_AD62_4e0d_96E9_5CB43AD0EDFD" visibility="public" base="EAID_11111111_5487_4080_A7F4_41526CB0AA00">
									<UML:ModelElement.stereotype>
										<UML:Stereotype name="metaclass"/>
									</UML:ModelElement.stereotype>
									<UML:ModelElement.taggedValue>
										<UML:TaggedValue tag="isAbstract" value="false"/>
										<UML:TaggedValue tag="isSpecification" value="false"/>
										<UML:TaggedValue tag="ea_stype" value="Sequence"/>
										<UML:TaggedValue tag="ea_ntype" value="0"/>
										<UML:TaggedValue tag="version" value="1.0"/>
										<UML:TaggedValue tag="isActive" value="false"/>
										<UML:TaggedValue tag="classifier" value="EAID_1F34ACFC_D0BC_45fd_987C_249E4ABB196A"/>
										<UML:TaggedValue tag="package" value="EAPK_6023FBC6_3BDD_4581_9AD7_EB479F476FBB"/>
										<UML:TaggedValue tag="classname" value="Driver"/>
										<UML:TaggedValue tag="date_created" value="2012-05-18 17:03:00"/>
										<UML:TaggedValue tag="date_modified" value="2012-05-18 17:03:00"/>
										<UML:TaggedValue tag="gentype" value="&lt;none&gt;"/>
										<UML:TaggedValue tag="tagged" value="0"/>
										<UML:TaggedValue tag="package_name" value="UC2C.10: Navigate to destination"/>
										<UML:TaggedValue tag="phase" value="1.0"/>
										<UML:TaggedValue tag="author" value="Fabio"/>
										<UML:TaggedValue tag="complexity" value="1"/>
										<UML:TaggedValue tag="status" value="Proposed"/>
										<UML:TaggedValue tag="stereotype" value="metaclass"/>
										<UML:TaggedValue tag="tpos" value="0"/>
										<UML:TaggedValue tag="ea_localid" value="13884"/>
										<UML:TaggedValue tag="ea_eleType" value="element"/>
										<UML:TaggedValue tag="style" value="BackColor=-1;BorderColor=-1;BorderWidth=-1;FontColor=-1;VSwimLanes=1;HSwimLanes=1;BorderStyle=0;"/>
										<UML:TaggedValue tag="$ea_xref_property" value="$XREFPROP=$XID={27C8FB28-990B-44f7-BA2F-0AE1D30042B5}$XID;$NAM=Stereotypes$NAM;$TYP=element property$TYP;$VIS=Public$VIS;$PAR=0$PAR;$DES=@STEREO;Name=metaclass;GUID={581F7887-6060-47ee-BAE6-FC8F8B1C0381};@ENDSTEREO;$DES;$CLT={1DEBE519-AD62-4e0d-96E9-5CB43AD0EDFD}$CLT;$SUP=&lt;none&gt;$SUP;$ENDXREF;"/>
									</UML:ModelElement.taggedValue>
								</UML:ClassifierRole>
								<UML:ClassifierRole xmi.id="EAID_4530C355_5245_4339_A236_4CC3D7277C8D" visibility="public" base="EAID_11111111_5487_4080_A7F4_41526CB0AA00">
									<UML:ModelElement.stereotype>
										<UML:Stereotype name="business actor"/>
									</UML:ModelElement.stereotype>
									<UML:ModelElement.taggedValue>
										<UML:TaggedValue tag="isAbstract" value="false"/>
										<UML:TaggedValue tag="isSpecification" value="false"/>
										<UML:TaggedValue tag="ea_stype" value="Sequence"/>
										<UML:TaggedValue tag="ea_ntype" value="0"/>
										<UML:TaggedValue tag="version" value="1.0"/>
										<UML:TaggedValue tag="isActive" value="false"/>
										<UML:TaggedValue tag="classifier" value="EAID_37C699B3_CEA1_43b3_B095_D7AF163B70C0"/>
										<UML:TaggedValue tag="package" value="EAPK_6023FBC6_3BDD_4581_9AD7_EB479F476FBB"/>
										<UML:TaggedValue tag="classname" value="Professional Driver"/>
										<UML:TaggedValue tag="date_created" value="2012-05-18 17:01:39"/>
										<UML:TaggedValue tag="date_modified" value="2012-05-18 17:01:39"/>
										<UML:TaggedValue tag="gentype" value="&lt;none&gt;"/>
										<UML:TaggedValue tag="tagged" value="0"/>
										<UML:TaggedValue tag="package_name" value="UC2C.10: Navigate to destination"/>
										<UML:TaggedValue tag="phase" value="1.0"/>
										<UML:TaggedValue tag="author" value="Fabio"/>
										<UML:TaggedValue tag="complexity" value="1"/>
										<UML:TaggedValue tag="status" value="Proposed"/>
										<UML:TaggedValue tag="stereotype" value="business actor"/>
										<UML:TaggedValue tag="tpos" value="0"/>
										<UML:TaggedValue tag="ea_localid" value="13882"/>
										<UML:TaggedValue tag="ea_eleType" value="element"/>
										<UML:TaggedValue tag="style" value="BackColor=-1;BorderColor=-1;BorderWidth=-1;FontColor=-1;VSwimLanes=1;HSwimLanes=1;BorderStyle=0;"/>
										<UML:TaggedValue tag="$ea_xref_property" value="$XREFPROP=$XID={E977545B-464E-41a8-BE71-E8399558A776}$XID;$NAM=Stereotypes$NAM;$TYP=element property$TYP;$VIS=Public$VIS;$PAR=0$PAR;$DES=@STEREO;Name=business actor;GUID={9FE5D0BB-625E-48cf-B034-0C69A44E5287};@ENDSTEREO;$DES;$CLT={4530C355-5245-4339-A236-4CC3D7277C8D}$CLT;$SUP=&lt;none&gt;$SUP;$ENDXREF;"/>
									</UML:ModelElement.taggedValue>
								</UML:ClassifierRole>
								<UML:ClassifierRole xmi.id="EAID_A06BA2A1_6E27_49ba_99C4_9CFE5C2987CF" visibility="public" base="EAID_11111111_5487_4080_A7F4_41526CB0AA00">
									<UML:ModelElement.stereotype>
										<UML:Stereotype name="business actor"/>
									</UML:ModelElement.stereotype>
									<UML:ModelElement.taggedValue>
										<UML:TaggedValue tag="isAbstract" value="false"/>
										<UML:TaggedValue tag="isSpecification" value="false"/>
										<UML:TaggedValue tag="ea_stype" value="Sequence"/>
										<UML:TaggedValue tag="ea_ntype" value="0"/>
										<UML:TaggedValue tag="version" value="1.0"/>
										<UML:TaggedValue tag="isActive" value="false"/>
										<UML:TaggedValue tag="classifier" value="EAID_37C699B3_CEA1_43b3_B095_D7AF163B70C0"/>
										<UML:TaggedValue tag="package" value="EAPK_6023FBC6_3BDD_4581_9AD7_EB479F476FBB"/>
										<UML:TaggedValue tag="classname" value="Professional Driver"/>
										<UML:TaggedValue tag="date_created" value="2012-05-18 17:03:14"/>
										<UML:TaggedValue tag="date_modified" value="2012-05-18 17:03:14"/>
										<UML:TaggedValue tag="gentype" value="&lt;none&gt;"/>
										<UML:TaggedValue tag="tagged" value="0"/>
										<UML:TaggedValue tag="package_name" value="UC2C.10: Navigate to destination"/>
										<UML:TaggedValue tag="phase" value="1.0"/>
										<UML:TaggedValue tag="author" value="Fabio"/>
										<UML:TaggedValue tag="complexity" value="1"/>
										<UML:TaggedValue tag="status" value="Proposed"/>
										<UML:TaggedValue tag="stereotype" value="business actor"/>
										<UML:TaggedValue tag="tpos" value="0"/>
										<UML:TaggedValue tag="ea_localid" value="13885"/>
										<UML:TaggedValue tag="ea_eleType" value="element"/>
										<UML:TaggedValue tag="style" value="BackColor=-1;BorderColor=-1;BorderWidth=-1;FontColor=-1;VSwimLanes=1;HSwimLanes=1;BorderStyle=0;"/>
										<UML:TaggedValue tag="$ea_xref_property" value="$XREFPROP=$XID={52DA01C7-F4E3-40c8-BD8A-151A0CEBF822}$XID;$NAM=Stereotypes$NAM;$TYP=element property$TYP;$VIS=Public$VIS;$PAR=0$PAR;$DES=@STEREO;Name=business actor;GUID={9FE5D0BB-625E-48cf-B034-0C69A44E5287};@ENDSTEREO;$DES;$CLT={A06BA2A1-6E27-49ba-99C4-9CFE5C2987CF}$CLT;$SUP=&lt;none&gt;$SUP;$ENDXREF;"/>
									</UML:ModelElement.taggedValue>
								</UML:ClassifierRole>
								<UML:ClassifierRole xmi.id="EAID_CD0F3A5E_96AF_44da_BDEA_2E420C9CA393" visibility="public" base="EAID_11111111_5487_4080_A7F4_41526CB0AA00">
									<UML:ModelElement.taggedValue>
										<UML:TaggedValue tag="isAbstract" value="false"/>
										<UML:TaggedValue tag="isSpecification" value="false"/>
										<UML:TaggedValue tag="ea_stype" value="Sequence"/>
										<UML:TaggedValue tag="ea_ntype" value="0"/>
										<UML:TaggedValue tag="version" value="1.0"/>
										<UML:TaggedValue tag="isActive" value="false"/>
										<UML:TaggedValue tag="classifier" value="EAID_9E6BBCC5_5EB7_43d4_94A1_A4619E9D5EC9"/>
										<UML:TaggedValue tag="package" value="EAPK_6023FBC6_3BDD_4581_9AD7_EB479F476FBB"/>
										<UML:TaggedValue tag="classname" value="Driver"/>
										<UML:TaggedValue tag="date_created" value="2012-05-18 17:02:23"/>
										<UML:TaggedValue tag="date_modified" value="2012-05-18 17:02:23"/>
										<UML:TaggedValue tag="gentype" value="&lt;none&gt;"/>
										<UML:TaggedValue tag="tagged" value="0"/>
										<UML:TaggedValue tag="package_name" value="UC2C.10: Navigate to destination"/>
										<UML:TaggedValue tag="phase" value="1.0"/>
										<UML:TaggedValue tag="author" value="Fabio"/>
										<UML:TaggedValue tag="complexity" value="1"/>
										<UML:TaggedValue tag="status" value="Proposed"/>
										<UML:TaggedValue tag="tpos" value="0"/>
										<UML:TaggedValue tag="ea_localid" value="13883"/>
										<UML:TaggedValue tag="ea_eleType" value="element"/>
										<UML:TaggedValue tag="style" value="BackColor=-1;BorderColor=-1;BorderWidth=-1;FontColor=-1;VSwimLanes=1;HSwimLanes=1;BorderStyle=0;"/>
									</UML:ModelElement.taggedValue>
								</UML:ClassifierRole>
							</UML:Namespace.ownedElement>
							<UML:Collaboration.interaction>
								<UML:Interaction xmi.id="EAID_6023FBC6_3BDD_4581_9AD7_EB479F476FBB_INT" name="EAID_6023FBC6_3BDD_4581_9AD7_EB479F476FBB_INT">
									<UML:Interaction.message>
										<UML:Message name="Request Location" xmi.id="EAID_F82F4867_6328_4b7d_BAED_81CBD7C2F8DF" visibility="public" sender="EAID_823C668C_7B9E_498f_83CA_11E81881EDF0" receiver="EAID_2ABA7B39_9B15_4c70_9EFB_614E31549B55">
											<UML:ModelElement.taggedValue>
												<UML:TaggedValue tag="style" value="1"/>
												<UML:TaggedValue tag="ea_type" value="Sequence"/>
												<UML:TaggedValue tag="direction" value="Source -&gt; Destination"/>
												<UML:TaggedValue tag="linemode" value="1"/>
												<UML:TaggedValue tag="linecolor" value="-1"/>
												<UML:TaggedValue tag="linewidth" value="0"/>
												<UML:TaggedValue tag="seqno" value="4"/>
												<UML:TaggedValue tag="headStyle" value="0"/>
												<UML:TaggedValue tag="lineStyle" value="0"/>
												<UML:TaggedValue tag="privatedata1" value="Synchronous"/>
												<UML:TaggedValue tag="privatedata2" value="retval=void;"/>
												<UML:TaggedValue tag="privatedata3" value="Call"/>
												<UML:TaggedValue tag="privatedata4" value="0"/>
												<UML:TaggedValue tag="ea_localid" value="14904"/>
												<UML:TaggedValue tag="ea_sourceType" value="Component"/>
												<UML:TaggedValue tag="ea_targetType" value="Component"/>
												<UML:TaggedValue tag="ea_sourceID" value="13888"/>
												<UML:TaggedValue tag="ea_targetID" value="13889"/>
												<UML:TaggedValue tag="src_visibility" value="Public"/>
												<UML:TaggedValue tag="src_isOrdered" value="false"/>
												<UML:TaggedValue tag="src_targetScope" value="instance"/>
												<UML:TaggedValue tag="src_changeable" value="none"/>
												<UML:TaggedValue tag="src_isNavigable" value="false"/>
												<UML:TaggedValue tag="src_containment" value="Unspecified"/>
												<UML:TaggedValue tag="src_style" value="Union=0;Derived=0;AllowDuplicates=0;Owned=0;Navigable=Non-Navigable;"/>
												<UML:TaggedValue tag="dst_visibility" value="Public"/>
												<UML:TaggedValue tag="dst_aggregation" value="0"/>
												<UML:TaggedValue tag="dst_isOrdered" value="false"/>
												<UML:TaggedValue tag="dst_targetScope" value="instance"/>
												<UML:TaggedValue tag="dst_changeable" value="none"/>
												<UML:TaggedValue tag="dst_isNavigable" value="true"/>
												<UML:TaggedValue tag="dst_containment" value="Unspecified"/>
												<UML:TaggedValue tag="dst_style" value="Union=0;Derived=0;AllowDuplicates=0;Owned=0;Navigable=Navigable;"/>
												<UML:TaggedValue tag="privatedata5" value="SX=0;SY=0;EX=0;EY=0;$LLB=;LLT=;LMT=CX=88:CY=13:OX=0:OY=0:HDN=0:BLD=0:ITA=0:UND=0:CLR=-1:ALN=0:DIR=0:ROT=0;LMB=;LRT=;LRB=;IRHS=;ILHS=;"/>
												<UML:TaggedValue tag="sequence_points" value="PtStartX=621;PtStartY=-256;PtEndX=773;PtEndY=-256;"/>
												<UML:TaggedValue tag="stateflags" value="Activation=0;"/>
												<UML:TaggedValue tag="virtualInheritance" value="0"/>
												<UML:TaggedValue tag="diagram" value="EAID_462B7E9F_9DB8_47b5_9A46_7DA59B6485A4"/>
												<UML:TaggedValue tag="mt" value="Request Location()"/>
											</UML:ModelElement.taggedValue>
										</UML:Message>
										<UML:Message name=": Location" xmi.id="EAID_FE680E98_6A9A_4207_97FD_5EAAEA0D0264" visibility="public" sender="EAID_2ABA7B39_9B15_4c70_9EFB_614E31549B55" receiver="EAID_823C668C_7B9E_498f_83CA_11E81881EDF0">
											<UML:ModelElement.taggedValue>
												<UML:TaggedValue tag="style" value="1"/>
												<UML:TaggedValue tag="ea_type" value="Sequence"/>
												<UML:TaggedValue tag="direction" value="Source -&gt; Destination"/>
												<UML:TaggedValue tag="linemode" value="1"/>
												<UML:TaggedValue tag="linecolor" value="-1"/>
												<UML:TaggedValue tag="linewidth" value="0"/>
												<UML:TaggedValue tag="seqno" value="5"/>
												<UML:TaggedValue tag="headStyle" value="0"/>
												<UML:TaggedValue tag="lineStyle" value="0"/>
												<UML:TaggedValue tag="privatedata1" value="Synchronous"/>
												<UML:TaggedValue tag="privatedata2" value="retval=void;"/>
												<UML:TaggedValue tag="privatedata3" value="Call"/>
												<UML:TaggedValue tag="privatedata4" value="1"/>
												<UML:TaggedValue tag="ea_localid" value="14905"/>
												<UML:TaggedValue tag="ea_sourceType" value="Component"/>
												<UML:TaggedValue tag="ea_targetType" value="Component"/>
												<UML:TaggedValue tag="ea_sourceID" value="13889"/>
												<UML:TaggedValue tag="ea_targetID" value="13888"/>
												<UML:TaggedValue tag="src_visibility" value="Public"/>
												<UML:TaggedValue tag="src_isOrdered" value="false"/>
												<UML:TaggedValue tag="src_targetScope" value="instance"/>
												<UML:TaggedValue tag="src_changeable" value="none"/>
												<UML:TaggedValue tag="src_isNavigable" value="false"/>
												<UML:TaggedValue tag="src_containment" value="Unspecified"/>
												<UML:TaggedValue tag="src_style" value="Union=0;Derived=0;AllowDuplicates=0;Owned=0;Navigable=Non-Navigable;"/>
												<UML:TaggedValue tag="dst_visibility" value="Public"/>
												<UML:TaggedValue tag="dst_aggregation" value="0"/>
												<UML:TaggedValue tag="dst_isOrdered" value="false"/>
												<UML:TaggedValue tag="dst_targetScope" value="instance"/>
												<UML:TaggedValue tag="dst_changeable" value="none"/>
												<UML:TaggedValue tag="dst_isNavigable" value="true"/>
												<UML:TaggedValue tag="dst_containment" value="Unspecified"/>
												<UML:TaggedValue tag="dst_style" value="Union=0;Derived=0;AllowDuplicates=0;Owned=0;Navigable=Navigable;"/>
												<UML:TaggedValue tag="privatedata5" value="SX=0;SY=0;EX=0;EY=0;$LLB=;LLT=;LMT=CX=53:CY=13:OX=0:OY=0:HDN=0:BLD=0:ITA=0:UND=0:CLR=-1:ALN=0:DIR=0:ROT=0;LMB=;LRT=;LRB=;IRHS=;ILHS=;"/>
												<UML:TaggedValue tag="sequence_points" value="PtStartX=774;PtStartY=-291;PtEndX=621;PtEndY=-291;"/>
												<UML:TaggedValue tag="stateflags" value="Activation=0;"/>
												<UML:TaggedValue tag="virtualInheritance" value="0"/>
												<UML:TaggedValue tag="diagram" value="EAID_462B7E9F_9DB8_47b5_9A46_7DA59B6485A4"/>
												<UML:TaggedValue tag="mt" value=": Location()"/>
											</UML:ModelElement.taggedValue>
										</UML:Message>
										<UML:Message name=": Traffic Status" xmi.id="EAID_18B4F0F7_0C5F_4100_B9FE_339C3F9292F3" visibility="public" sender="EAID_BF980BBF_FDCB_4dbc_BB2F_2F838F342E74" receiver="EAID_823C668C_7B9E_498f_83CA_11E81881EDF0">
											<UML:ModelElement.taggedValue>
												<UML:TaggedValue tag="style" value="1"/>
												<UML:TaggedValue tag="ea_type" value="Sequence"/>
												<UML:TaggedValue tag="direction" value="Source -&gt; Destination"/>
												<UML:TaggedValue tag="linemode" value="1"/>
												<UML:TaggedValue tag="linecolor" value="-1"/>
												<UML:TaggedValue tag="linewidth" value="0"/>
												<UML:TaggedValue tag="seqno" value="7"/>
												<UML:TaggedValue tag="headStyle" value="0"/>
												<UML:TaggedValue tag="lineStyle" value="0"/>
												<UML:TaggedValue tag="privatedata1" value="Synchronous"/>
												<UML:TaggedValue tag="privatedata2" value="retval=void;"/>
												<UML:TaggedValue tag="privatedata3" value="Call"/>
												<UML:TaggedValue tag="privatedata4" value="0"/>
												<UML:TaggedValue tag="ea_localid" value="14989"/>
												<UML:TaggedValue tag="ea_sourceName" value="Multi-Modal Mobility"/>
												<UML:TaggedValue tag="ea_sourceType" value="Package"/>
												<UML:TaggedValue tag="ea_targetType" value="Component"/>
												<UML:TaggedValue tag="ea_sourceID" value="13892"/>
												<UML:TaggedValue tag="ea_targetID" value="13888"/>
												<UML:TaggedValue tag="src_visibility" value="Public"/>
												<UML:TaggedValue tag="src_isOrdered" value="false"/>
												<UML:TaggedValue tag="src_targetScope" value="instance"/>
												<UML:TaggedValue tag="src_changeable" value="none"/>
												<UML:TaggedValue tag="src_isNavigable" value="false"/>
												<UML:TaggedValue tag="src_containment" value="Unspecified"/>
												<UML:TaggedValue tag="src_style" value="Union=0;Derived=0;AllowDuplicates=0;Owned=0;Navigable=Non-Navigable;"/>
												<UML:TaggedValue tag="dst_visibility" value="Public"/>
												<UML:TaggedValue tag="dst_aggregation" value="0"/>
												<UML:TaggedValue tag="dst_isOrdered" value="false"/>
												<UML:TaggedValue tag="dst_targetScope" value="instance"/>
												<UML:TaggedValue tag="dst_changeable" value="none"/>
												<UML:TaggedValue tag="dst_isNavigable" value="true"/>
												<UML:TaggedValue tag="dst_containment" value="Unspecified"/>
												<UML:TaggedValue tag="dst_style" value="Union=0;Derived=0;AllowDuplicates=0;Owned=0;Navigable=Navigable;"/>
												<UML:TaggedValue tag="privatedata5" value="SX=0;SY=0;EX=0;EY=0;$LLB=;LLT=;LMT=CX=74:CY=13:OX=0:OY=0:HDN=0:BLD=0:ITA=0:UND=0:CLR=-1:ALN=0:DIR=0:ROT=0;LMB=;LRT=;LRB=;IRHS=;ILHS=;"/>
												<UML:TaggedValue tag="sequence_points" value="PtStartX=966;PtStartY=-367;PtEndX=621;PtEndY=-367;"/>
												<UML:TaggedValue tag="stateflags" value="Activation=0;"/>
												<UML:TaggedValue tag="virtualInheritance" value="0"/>
												<UML:TaggedValue tag="diagram" value="EAID_462B7E9F_9DB8_47b5_9A46_7DA59B6485A4"/>
												<UML:TaggedValue tag="mt" value=": Traffic Status()"/>
											</UML:ModelElement.taggedValue>
										</UML:Message>
										<UML:Message name="Request Traffic Status" xmi.id="EAID_4BECD11F_635D_4488_91F7_5FA53180BA4C" visibility="public" sender="EAID_823C668C_7B9E_498f_83CA_11E81881EDF0" receiver="EAID_BF980BBF_FDCB_4dbc_BB2F_2F838F342E74">
											<UML:ModelElement.taggedValue>
												<UML:TaggedValue tag="style" value="1"/>
												<UML:TaggedValue tag="ea_type" value="Sequence"/>
												<UML:TaggedValue tag="direction" value="Source -&gt; Destination"/>
												<UML:TaggedValue tag="linemode" value="1"/>
												<UML:TaggedValue tag="linecolor" value="-1"/>
												<UML:TaggedValue tag="linewidth" value="0"/>
												<UML:TaggedValue tag="seqno" value="6"/>
												<UML:TaggedValue tag="headStyle" value="0"/>
												<UML:TaggedValue tag="lineStyle" value="0"/>
												<UML:TaggedValue tag="privatedata1" value="Synchronous"/>
												<UML:TaggedValue tag="privatedata2" value="retval=void;"/>
												<UML:TaggedValue tag="privatedata3" value="Call"/>
												<UML:TaggedValue tag="privatedata4" value="0"/>
												<UML:TaggedValue tag="ea_localid" value="14908"/>
												<UML:TaggedValue tag="ea_targetName" value="Multi-Modal Mobility"/>
												<UML:TaggedValue tag="ea_sourceType" value="Component"/>
												<UML:TaggedValue tag="ea_targetType" value="Package"/>
												<UML:TaggedValue tag="ea_sourceID" value="13888"/>
												<UML:TaggedValue tag="ea_targetID" value="13892"/>
												<UML:TaggedValue tag="src_visibility" value="Public"/>
												<UML:TaggedValue tag="src_isOrdered" value="false"/>
												<UML:TaggedValue tag="src_targetScope" value="instance"/>
												<UML:TaggedValue tag="src_changeable" value="none"/>
												<UML:TaggedValue tag="src_isNavigable" value="false"/>
												<UML:TaggedValue tag="src_containment" value="Unspecified"/>
												<UML:TaggedValue tag="src_style" value="Union=0;Derived=0;AllowDuplicates=0;Owned=0;Navigable=Non-Navigable;"/>
												<UML:TaggedValue tag="dst_visibility" value="Public"/>
												<UML:TaggedValue tag="dst_aggregation" value="0"/>
												<UML:TaggedValue tag="dst_isOrdered" value="false"/>
												<UML:TaggedValue tag="dst_targetScope" value="instance"/>
												<UML:TaggedValue tag="dst_changeable" value="none"/>
												<UML:TaggedValue tag="dst_isNavigable" value="true"/>
												<UML:TaggedValue tag="dst_containment" value="Unspecified"/>
												<UML:TaggedValue tag="dst_style" value="Union=0;Derived=0;AllowDuplicates=0;Owned=0;Navigable=Navigable;"/>
												<UML:TaggedValue tag="privatedata5" value="SX=0;SY=-6;EX=0;EY=0;$LLB=;LLT=;LMT=CX=109:CY=13:OX=0:OY=0:HDN=0:BLD=0:ITA=0:UND=0:CLR=-1:ALN=0:DIR=0:ROT=0;LMB=;LRT=;LRB=;IRHS=;ILHS=;"/>
												<UML:TaggedValue tag="sequence_points" value="PtStartX=621;PtStartY=-332;PtEndX=965;PtEndY=-332;"/>
												<UML:TaggedValue tag="stateflags" value="Activation=0;"/>
												<UML:TaggedValue tag="virtualInheritance" value="0"/>
												<UML:TaggedValue tag="diagram" value="EAID_462B7E9F_9DB8_47b5_9A46_7DA59B6485A4"/>
												<UML:TaggedValue tag="mt" value="Request Traffic Status()"/>
											</UML:ModelElement.taggedValue>
										</UML:Message>
										<UML:Message name="Start Navigation" xmi.id="EAID_BD45A363_573B_47ba_A91E_33A622825681" visibility="public" sender="EAID_840C01B4_2BD9_4605_AE55_E8216334F374" receiver="EAID_823C668C_7B9E_498f_83CA_11E81881EDF0">
											<UML:ModelElement.taggedValue>
												<UML:TaggedValue tag="style" value="1"/>
												<UML:TaggedValue tag="ea_type" value="Sequence"/>
												<UML:TaggedValue tag="direction" value="Source -&gt; Destination"/>
												<UML:TaggedValue tag="linemode" value="1"/>
												<UML:TaggedValue tag="linecolor" value="-1"/>
												<UML:TaggedValue tag="linewidth" value="0"/>
												<UML:TaggedValue tag="seqno" value="3"/>
												<UML:TaggedValue tag="headStyle" value="0"/>
												<UML:TaggedValue tag="lineStyle" value="0"/>
												<UML:TaggedValue tag="privatedata1" value="Synchronous"/>
												<UML:TaggedValue tag="privatedata2" value="retval=void;"/>
												<UML:TaggedValue tag="privatedata3" value="Call"/>
												<UML:TaggedValue tag="privatedata4" value="0"/>
												<UML:TaggedValue tag="ea_localid" value="14903"/>
												<UML:TaggedValue tag="ea_sourceType" value="Component"/>
												<UML:TaggedValue tag="ea_targetType" value="Component"/>
												<UML:TaggedValue tag="ea_sourceID" value="13887"/>
												<UML:TaggedValue tag="ea_targetID" value="13888"/>
												<UML:TaggedValue tag="src_visibility" value="Public"/>
												<UML:TaggedValue tag="src_isOrdered" value="false"/>
												<UML:TaggedValue tag="src_targetScope" value="instance"/>
												<UML:TaggedValue tag="src_changeable" value="none"/>
												<UML:TaggedValue tag="src_isNavigable" value="false"/>
												<UML:TaggedValue tag="src_containment" value="Unspecified"/>
												<UML:TaggedValue tag="src_style" value="Union=0;Derived=0;AllowDuplicates=0;Owned=0;Navigable=Non-Navigable;"/>
												<UML:TaggedValue tag="dst_visibility" value="Public"/>
												<UML:TaggedValue tag="dst_aggregation" value="0"/>
												<UML:TaggedValue tag="dst_isOrdered" value="false"/>
												<UML:TaggedValue tag="dst_targetScope" value="instance"/>
												<UML:TaggedValue tag="dst_changeable" value="none"/>
												<UML:TaggedValue tag="dst_isNavigable" value="true"/>
												<UML:TaggedValue tag="dst_containment" value="Unspecified"/>
												<UML:TaggedValue tag="dst_style" value="Union=0;Derived=0;AllowDuplicates=0;Owned=0;Navigable=Navigable;"/>
												<UML:TaggedValue tag="privatedata5" value="SX=0;SY=-3;EX=0;EY=0;$LLB=;LLT=;LMT=CX=82:CY=13:OX=0:OY=0:HDN=0:BLD=0:ITA=0:UND=0:CLR=-1:ALN=0:DIR=0:ROT=0;LMB=;LRT=;LRB=;IRHS=;ILHS=;"/>
												<UML:TaggedValue tag="sequence_points" value="PtStartX=445;PtStartY=-221;PtEndX=610;PtEndY=-221;"/>
												<UML:TaggedValue tag="stateflags" value="Activation=0;"/>
												<UML:TaggedValue tag="virtualInheritance" value="0"/>
												<UML:TaggedValue tag="diagram" value="EAID_462B7E9F_9DB8_47b5_9A46_7DA59B6485A4"/>
												<UML:TaggedValue tag="mt" value="Start Navigation()"/>
											</UML:ModelElement.taggedValue>
										</UML:Message>
										<UML:Message name="Compute Route" xmi.id="EAID_C109F109_FA23_481e_AC8A_238D50C46B9D" visibility="public" sender="EAID_823C668C_7B9E_498f_83CA_11E81881EDF0" receiver="EAID_823C668C_7B9E_498f_83CA_11E81881EDF0">
											<UML:ModelElement.taggedValue>
												<UML:TaggedValue tag="style" value="1"/>
												<UML:TaggedValue tag="ea_type" value="Sequence"/>
												<UML:TaggedValue tag="direction" value="Source -&gt; Destination"/>
												<UML:TaggedValue tag="linemode" value="1"/>
												<UML:TaggedValue tag="linecolor" value="-1"/>
												<UML:TaggedValue tag="linewidth" value="0"/>
												<UML:TaggedValue tag="seqno" value="8"/>
												<UML:TaggedValue tag="headStyle" value="0"/>
												<UML:TaggedValue tag="lineStyle" value="0"/>
												<UML:TaggedValue tag="privatedata1" value="Synchronous"/>
												<UML:TaggedValue tag="privatedata2" value="retval=void;"/>
												<UML:TaggedValue tag="privatedata3" value="Call"/>
												<UML:TaggedValue tag="privatedata4" value="0"/>
												<UML:TaggedValue tag="ea_localid" value="14907"/>
												<UML:TaggedValue tag="ea_sourceType" value="Component"/>
												<UML:TaggedValue tag="ea_targetType" value="Component"/>
												<UML:TaggedValue tag="ea_sourceID" value="13888"/>
												<UML:TaggedValue tag="ea_targetID" value="13888"/>
												<UML:TaggedValue tag="src_visibility" value="Public"/>
												<UML:TaggedValue tag="src_isOrdered" value="false"/>
												<UML:TaggedValue tag="src_targetScope" value="instance"/>
												<UML:TaggedValue tag="src_changeable" value="none"/>
												<UML:TaggedValue tag="src_isNavigable" value="false"/>
												<UML:TaggedValue tag="src_containment" value="Unspecified"/>
												<UML:TaggedValue tag="src_style" value="Union=0;Derived=0;AllowDuplicates=0;Owned=0;Navigable=Non-Navigable;"/>
												<UML:TaggedValue tag="dst_visibility" value="Public"/>
												<UML:TaggedValue tag="dst_aggregation" value="0"/>
												<UML:TaggedValue tag="dst_isOrdered" value="false"/>
												<UML:TaggedValue tag="dst_targetScope" value="instance"/>
												<UML:TaggedValue tag="dst_changeable" value="none"/>
												<UML:TaggedValue tag="dst_isNavigable" value="true"/>
												<UML:TaggedValue tag="dst_containment" value="Unspecified"/>
												<UML:TaggedValue tag="dst_style" value="Union=0;Derived=0;AllowDuplicates=0;Owned=0;Navigable=Navigable;"/>
												<UML:TaggedValue tag="privatedata5" value="SX=0;SY=0;EX=0;EY=0;$LLB=;LLT=;LMT=CX=103:CY=13:OX=40:OY=15:HDN=0:BLD=0:ITA=0:UND=0:CLR=-1:ALN=0:DIR=0:ROT=0;LMB=;LRT=;LRB=;IRHS=;ILHS=;"/>
												<UML:TaggedValue tag="sequence_points" value="PtStartX=621;PtStartY=-402;PtEndX=626;PtEndY=-417;"/>
												<UML:TaggedValue tag="stateflags" value="Activation=0;"/>
												<UML:TaggedValue tag="virtualInheritance" value="0"/>
												<UML:TaggedValue tag="diagram" value="EAID_462B7E9F_9DB8_47b5_9A46_7DA59B6485A4"/>
												<UML:TaggedValue tag="mt" value="Compute Route()"/>
											</UML:ModelElement.taggedValue>
										</UML:Message>
										<UML:Message name=": Driving instruction" xmi.id="EAID_F6017B6D_F852_47ed_A178_C7803D5094D7" visibility="public" sender="EAID_823C668C_7B9E_498f_83CA_11E81881EDF0" receiver="EAID_840C01B4_2BD9_4605_AE55_E8216334F374">
											<UML:ModelElement.taggedValue>
												<UML:TaggedValue tag="style" value="1"/>
												<UML:TaggedValue tag="ea_type" value="Sequence"/>
												<UML:TaggedValue tag="direction" value="Source -&gt; Destination"/>
												<UML:TaggedValue tag="linemode" value="1"/>
												<UML:TaggedValue tag="linecolor" value="-1"/>
												<UML:TaggedValue tag="linewidth" value="0"/>
												<UML:TaggedValue tag="seqno" value="9"/>
												<UML:TaggedValue tag="headStyle" value="0"/>
												<UML:TaggedValue tag="lineStyle" value="0"/>
												<UML:TaggedValue tag="privatedata1" value="Synchronous"/>
												<UML:TaggedValue tag="privatedata2" value="retval=void;"/>
												<UML:TaggedValue tag="privatedata3" value="Call"/>
												<UML:TaggedValue tag="privatedata4" value="0"/>
												<UML:TaggedValue tag="ea_localid" value="14990"/>
												<UML:TaggedValue tag="ea_sourceType" value="Component"/>
												<UML:TaggedValue tag="ea_targetType" value="Component"/>
												<UML:TaggedValue tag="ea_sourceID" value="13888"/>
												<UML:TaggedValue tag="ea_targetID" value="13887"/>
												<UML:TaggedValue tag="src_visibility" value="Public"/>
												<UML:TaggedValue tag="src_isOrdered" value="false"/>
												<UML:TaggedValue tag="src_targetScope" value="instance"/>
												<UML:TaggedValue tag="src_changeable" value="none"/>
												<UML:TaggedValue tag="src_isNavigable" value="false"/>
												<UML:TaggedValue tag="src_containment" value="Unspecified"/>
												<UML:TaggedValue tag="src_style" value="Union=0;Derived=0;AllowDuplicates=0;Owned=0;Navigable=Non-Navigable;"/>
												<UML:TaggedValue tag="dst_visibility" value="Public"/>
												<UML:TaggedValue tag="dst_aggregation" value="0"/>
												<UML:TaggedValue tag="dst_isOrdered" value="false"/>
												<UML:TaggedValue tag="dst_targetScope" value="instance"/>
												<UML:TaggedValue tag="dst_changeable" value="none"/>
												<UML:TaggedValue tag="dst_isNavigable" value="true"/>
												<UML:TaggedValue tag="dst_containment" value="Unspecified"/>
												<UML:TaggedValue tag="dst_style" value="Union=0;Derived=0;AllowDuplicates=0;Owned=0;Navigable=Navigable;"/>
												<UML:TaggedValue tag="privatedata5" value="SX=0;SY=0;EX=0;EY=0;$LLB=;LLT=;LMT=CX=96:CY=13:OX=0:OY=0:HDN=0:BLD=0:ITA=0:UND=0:CLR=-1:ALN=0:DIR=0:ROT=0;LMB=;LRT=;LRB=;IRHS=;ILHS=;"/>
												<UML:TaggedValue tag="sequence_points" value="PtStartX=611;PtStartY=-437;PtEndX=445;PtEndY=-437;"/>
												<UML:TaggedValue tag="virtualInheritance" value="0"/>
												<UML:TaggedValue tag="diagram" value="EAID_462B7E9F_9DB8_47b5_9A46_7DA59B6485A4"/>
												<UML:TaggedValue tag="mt" value=": Driving instruction()"/>
											</UML:ModelElement.taggedValue>
										</UML:Message>
										<UML:Message name="Start Navigation" xmi.id="EAID_D8291BFF_C3B2_4c56_8017_CFDC893A838B" visibility="public" sender="EAID_CAAA160F_A319_4587_A090_0CD6A814D41A" receiver="EAID_840C01B4_2BD9_4605_AE55_E8216334F374">
											<UML:ModelElement.taggedValue>
												<UML:TaggedValue tag="style" value="1"/>
												<UML:TaggedValue tag="ea_type" value="Sequence"/>
												<UML:TaggedValue tag="direction" value="Source -&gt; Destination"/>
												<UML:TaggedValue tag="linemode" value="1"/>
												<UML:TaggedValue tag="linecolor" value="-1"/>
												<UML:TaggedValue tag="linewidth" value="0"/>
												<UML:TaggedValue tag="seqno" value="2"/>
												<UML:TaggedValue tag="headStyle" value="0"/>
												<UML:TaggedValue tag="lineStyle" value="0"/>
												<UML:TaggedValue tag="privatedata1" value="Synchronous"/>
												<UML:TaggedValue tag="privatedata2" value="retval=void;"/>
												<UML:TaggedValue tag="privatedata3" value="Call"/>
												<UML:TaggedValue tag="privatedata4" value="0"/>
												<UML:TaggedValue tag="ea_localid" value="14902"/>
												<UML:TaggedValue tag="ea_sourceType" value="Component"/>
												<UML:TaggedValue tag="ea_targetType" value="Component"/>
												<UML:TaggedValue tag="ea_sourceID" value="13886"/>
												<UML:TaggedValue tag="ea_targetID" value="13887"/>
												<UML:TaggedValue tag="src_visibility" value="Public"/>
												<UML:TaggedValue tag="src_isOrdered" value="false"/>
												<UML:TaggedValue tag="src_targetScope" value="instance"/>
												<UML:TaggedValue tag="src_changeable" value="none"/>
												<UML:TaggedValue tag="src_isNavigable" value="false"/>
												<UML:TaggedValue tag="src_containment" value="Unspecified"/>
												<UML:TaggedValue tag="src_style" value="Union=0;Derived=0;AllowDuplicates=0;Owned=0;Navigable=Non-Navigable;"/>
												<UML:TaggedValue tag="dst_visibility" value="Public"/>
												<UML:TaggedValue tag="dst_aggregation" value="0"/>
												<UML:TaggedValue tag="dst_isOrdered" value="false"/>
												<UML:TaggedValue tag="dst_targetScope" value="instance"/>
												<UML:TaggedValue tag="dst_changeable" value="none"/>
												<UML:TaggedValue tag="dst_isNavigable" value="true"/>
												<UML:TaggedValue tag="dst_containment" value="Unspecified"/>
												<UML:TaggedValue tag="dst_style" value="Union=0;Derived=0;AllowDuplicates=0;Owned=0;Navigable=Navigable;"/>
												<UML:TaggedValue tag="privatedata5" value="SX=0;SY=-13;EX=0;EY=0;$LLB=;LLT=;LMT=CX=82:CY=13:OX=0:OY=0:HDN=0:BLD=0:ITA=0:UND=0:CLR=-1:ALN=0:DIR=0:ROT=0;LMB=;LRT=;LRB=;IRHS=;ILHS=;"/>
												<UML:TaggedValue tag="sequence_points" value="PtStartX=268;PtStartY=-183;PtEndX=434;PtEndY=-183;"/>
												<UML:TaggedValue tag="stateflags" value="Activation=0;"/>
												<UML:TaggedValue tag="virtualInheritance" value="0"/>
												<UML:TaggedValue tag="diagram" value="EAID_462B7E9F_9DB8_47b5_9A46_7DA59B6485A4"/>
												<UML:TaggedValue tag="mt" value="Start Navigation()"/>
											</UML:ModelElement.taggedValue>
										</UML:Message>
										<UML:Message name=": Driving instruction" xmi.id="EAID_FC85C7DA_091F_43f6_AABB_719D759B100D" visibility="public" sender="EAID_840C01B4_2BD9_4605_AE55_E8216334F374" receiver="EAID_CAAA160F_A319_4587_A090_0CD6A814D41A">
											<UML:ModelElement.taggedValue>
												<UML:TaggedValue tag="style" value="1"/>
												<UML:TaggedValue tag="ea_type" value="Sequence"/>
												<UML:TaggedValue tag="direction" value="Source -&gt; Destination"/>
												<UML:TaggedValue tag="linemode" value="1"/>
												<UML:TaggedValue tag="linecolor" value="-1"/>
												<UML:TaggedValue tag="linewidth" value="0"/>
												<UML:TaggedValue tag="seqno" value="10"/>
												<UML:TaggedValue tag="headStyle" value="0"/>
												<UML:TaggedValue tag="lineStyle" value="0"/>
												<UML:TaggedValue tag="privatedata1" value="Synchronous"/>
												<UML:TaggedValue tag="privatedata2" value="retval=void;"/>
												<UML:TaggedValue tag="privatedata3" value="Call"/>
												<UML:TaggedValue tag="privatedata4" value="0"/>
												<UML:TaggedValue tag="ea_localid" value="14991"/>
												<UML:TaggedValue tag="ea_sourceType" value="Component"/>
												<UML:TaggedValue tag="ea_targetType" value="Component"/>
												<UML:TaggedValue tag="ea_sourceID" value="13887"/>
												<UML:TaggedValue tag="ea_targetID" value="13886"/>
												<UML:TaggedValue tag="src_visibility" value="Public"/>
												<UML:TaggedValue tag="src_isOrdered" value="false"/>
												<UML:TaggedValue tag="src_targetScope" value="instance"/>
												<UML:TaggedValue tag="src_changeable" value="none"/>
												<UML:TaggedValue tag="src_isNavigable" value="false"/>
												<UML:TaggedValue tag="src_containment" value="Unspecified"/>
												<UML:TaggedValue tag="src_style" value="Union=0;Derived=0;AllowDuplicates=0;Owned=0;Navigable=Non-Navigable;"/>
												<UML:TaggedValue tag="dst_visibility" value="Public"/>
												<UML:TaggedValue tag="dst_aggregation" value="0"/>
												<UML:TaggedValue tag="dst_isOrdered" value="false"/>
												<UML:TaggedValue tag="dst_targetScope" value="instance"/>
												<UML:TaggedValue tag="dst_changeable" value="none"/>
												<UML:TaggedValue tag="dst_isNavigable" value="true"/>
												<UML:TaggedValue tag="dst_containment" value="Unspecified"/>
												<UML:TaggedValue tag="dst_style" value="Union=0;Derived=0;AllowDuplicates=0;Owned=0;Navigable=Navigable;"/>
												<UML:TaggedValue tag="privatedata5" value="SX=0;SY=0;EX=0;EY=0;$LLB=;LLT=;LMT=CX=96:CY=13:OX=0:OY=0:HDN=0:BLD=0:ITA=0:UND=0:CLR=-1:ALN=0:DIR=0:ROT=0;LMB=;LRT=;LRB=;IRHS=;ILHS=;"/>
												<UML:TaggedValue tag="sequence_points" value="PtStartX=435;PtStartY=-472;PtEndX=268;PtEndY=-472;"/>
												<UML:TaggedValue tag="stateflags" value="Activation=0;"/>
												<UML:TaggedValue tag="virtualInheritance" value="0"/>
												<UML:TaggedValue tag="diagram" value="EAID_462B7E9F_9DB8_47b5_9A46_7DA59B6485A4"/>
												<UML:TaggedValue tag="mt" value=": Driving instruction()"/>
											</UML:ModelElement.taggedValue>
										</UML:Message>
										<UML:Message name=": Driving instruction" xmi.id="EAID_3035E43E_4287_4f92_9F61_43A06C521238" visibility="public" sender="EAID_CAAA160F_A319_4587_A090_0CD6A814D41A" receiver="EAID_A06BA2A1_6E27_49ba_99C4_9CFE5C2987CF">
											<UML:ModelElement.taggedValue>
												<UML:TaggedValue tag="style" value="1"/>
												<UML:TaggedValue tag="ea_type" value="Sequence"/>
												<UML:TaggedValue tag="direction" value="Source -&gt; Destination"/>
												<UML:TaggedValue tag="linemode" value="1"/>
												<UML:TaggedValue tag="linecolor" value="-1"/>
												<UML:TaggedValue tag="linewidth" value="0"/>
												<UML:TaggedValue tag="seqno" value="11"/>
												<UML:TaggedValue tag="headStyle" value="0"/>
												<UML:TaggedValue tag="lineStyle" value="0"/>
												<UML:TaggedValue tag="privatedata1" value="Synchronous"/>
												<UML:TaggedValue tag="privatedata2" value="retval=void;"/>
												<UML:TaggedValue tag="privatedata3" value="Call"/>
												<UML:TaggedValue tag="privatedata4" value="0"/>
												<UML:TaggedValue tag="ea_localid" value="14993"/>
												<UML:TaggedValue tag="ea_sourceType" value="Component"/>
												<UML:TaggedValue tag="ea_targetType" value="Sequence"/>
												<UML:TaggedValue tag="ea_sourceID" value="13886"/>
												<UML:TaggedValue tag="ea_targetID" value="13885"/>
												<UML:TaggedValue tag="src_visibility" value="Public"/>
												<UML:TaggedValue tag="src_isOrdered" value="false"/>
												<UML:TaggedValue tag="src_targetScope" value="instance"/>
												<UML:TaggedValue tag="src_changeable" value="none"/>
												<UML:TaggedValue tag="src_isNavigable" value="false"/>
												<UML:TaggedValue tag="src_containment" value="Unspecified"/>
												<UML:TaggedValue tag="src_style" value="Union=0;Derived=0;AllowDuplicates=0;Owned=0;Navigable=Non-Navigable;"/>
												<UML:TaggedValue tag="dst_visibility" value="Public"/>
												<UML:TaggedValue tag="dst_aggregation" value="0"/>
												<UML:TaggedValue tag="dst_isOrdered" value="false"/>
												<UML:TaggedValue tag="dst_targetScope" value="instance"/>
												<UML:TaggedValue tag="dst_changeable" value="none"/>
												<UML:TaggedValue tag="dst_isNavigable" value="true"/>
												<UML:TaggedValue tag="dst_containment" value="Unspecified"/>
												<UML:TaggedValue tag="dst_style" value="Union=0;Derived=0;AllowDuplicates=0;Owned=0;Navigable=Navigable;"/>
												<UML:TaggedValue tag="privatedata5" value="SX=0;SY=0;EX=0;EY=0;$LLB=;LLT=;LMT=CX=96:CY=13:OX=0:OY=0:HDN=0:BLD=0:ITA=0:UND=0:CLR=-1:ALN=0:DIR=0:ROT=0;LMB=;LRT=;LRB=;IRHS=;ILHS=;"/>
												<UML:TaggedValue tag="sequence_points" value="PtStartX=258;PtStartY=-507;PtEndX=115;PtEndY=-507;"/>
												<UML:TaggedValue tag="virtualInheritance" value="0"/>
												<UML:TaggedValue tag="diagram" value="EAID_462B7E9F_9DB8_47b5_9A46_7DA59B6485A4"/>
												<UML:TaggedValue tag="mt" value=": Driving instruction()"/>
											</UML:ModelElement.taggedValue>
										</UML:Message>
										<UML:Message name="Start Navigation" xmi.id="EAID_F07C3E81_4C6F_4419_8BB1_BE7014FCBB04" visibility="public" sender="EAID_A06BA2A1_6E27_49ba_99C4_9CFE5C2987CF" receiver="EAID_CAAA160F_A319_4587_A090_0CD6A814D41A">
											<UML:ModelElement.taggedValue>
												<UML:TaggedValue tag="style" value="1"/>
												<UML:TaggedValue tag="ea_type" value="Sequence"/>
												<UML:TaggedValue tag="direction" value="Source -&gt; Destination"/>
												<UML:TaggedValue tag="linemode" value="1"/>
												<UML:TaggedValue tag="linecolor" value="-1"/>
												<UML:TaggedValue tag="linewidth" value="0"/>
												<UML:TaggedValue tag="seqno" value="1"/>
												<UML:TaggedValue tag="headStyle" value="0"/>
												<UML:TaggedValue tag="lineStyle" value="0"/>
												<UML:TaggedValue tag="privatedata1" value="Synchronous"/>
												<UML:TaggedValue tag="privatedata2" value="retval=void;"/>
												<UML:TaggedValue tag="privatedata3" value="Call"/>
												<UML:TaggedValue tag="privatedata4" value="0"/>
												<UML:TaggedValue tag="ea_localid" value="14901"/>
												<UML:TaggedValue tag="ea_sourceType" value="Sequence"/>
												<UML:TaggedValue tag="ea_targetType" value="Component"/>
												<UML:TaggedValue tag="ea_sourceID" value="13885"/>
												<UML:TaggedValue tag="ea_targetID" value="13886"/>
												<UML:TaggedValue tag="src_visibility" value="Public"/>
												<UML:TaggedValue tag="src_isOrdered" value="false"/>
												<UML:TaggedValue tag="src_targetScope" value="instance"/>
												<UML:TaggedValue tag="src_changeable" value="none"/>
												<UML:TaggedValue tag="src_isNavigable" value="false"/>
												<UML:TaggedValue tag="src_containment" value="Unspecified"/>
												<UML:TaggedValue tag="src_style" value="Union=0;Derived=0;AllowDuplicates=0;Owned=0;Navigable=Non-Navigable;"/>
												<UML:TaggedValue tag="dst_visibility" value="Public"/>
												<UML:TaggedValue tag="dst_aggregation" value="0"/>
												<UML:TaggedValue tag="dst_isOrdered" value="false"/>
												<UML:TaggedValue tag="dst_targetScope" value="instance"/>
												<UML:TaggedValue tag="dst_changeable" value="none"/>
												<UML:TaggedValue tag="dst_isNavigable" value="true"/>
												<UML:TaggedValue tag="dst_containment" value="Unspecified"/>
												<UML:TaggedValue tag="dst_style" value="Union=0;Derived=0;AllowDuplicates=0;Owned=0;Navigable=Navigable;"/>
												<UML:TaggedValue tag="privatedata5" value="SX=0;SY=0;EX=0;EY=0;$LLB=;LLT=;LMT=CX=82:CY=13:OX=0:OY=0:HDN=0:BLD=0:ITA=0:UND=0:CLR=-1:ALN=0:DIR=0:ROT=0;LMB=;LRT=;LRB=;IRHS=;ILHS=;"/>
												<UML:TaggedValue tag="sequence_points" value="PtStartX=115;PtStartY=-135;PtEndX=257;PtEndY=-135;"/>
												<UML:TaggedValue tag="stateflags" value="Activation=0;ExtendActivationUp=0;"/>
												<UML:TaggedValue tag="virtualInheritance" value="0"/>
												<UML:TaggedValue tag="diagram" value="EAID_462B7E9F_9DB8_47b5_9A46_7DA59B6485A4"/>
												<UML:TaggedValue tag="mt" value="Start Navigation()"/>
											</UML:ModelElement.taggedValue>
										</UML:Message>
									</UML:Interaction.message>
								</UML:Interaction>
							</UML:Collaboration.interaction>
						</UML:Collaboration>
						<UML:Component xmi.id="EAID_2ABA7B39_9B15_4c70_9EFB_614E31549B55" visibility="public" namespace="EAPK_6023FBC6_3BDD_4581_9AD7_EB479F476FBB" isRoot="false" isLeaf="false" isAbstract="false">
							<UML:ModelElement.taggedValue>
								<UML:TaggedValue tag="isSpecification" value="false"/>
								<UML:TaggedValue tag="ea_stype" value="Component"/>
								<UML:TaggedValue tag="ea_ntype" value="0"/>
								<UML:TaggedValue tag="version" value="1.0"/>
								<UML:TaggedValue tag="isActive" value="false"/>
								<UML:TaggedValue tag="classifier" value="EAID_C24E7F9D_247B_4a69_A041_1DAE8DC85DB1"/>
								<UML:TaggedValue tag="package" value="EAPK_6023FBC6_3BDD_4581_9AD7_EB479F476FBB"/>
								<UML:TaggedValue tag="classname" value="Geolocation module"/>
								<UML:TaggedValue tag="date_created" value="2012-05-18 17:06:04"/>
								<UML:TaggedValue tag="date_modified" value="2012-05-18 17:06:04"/>
								<UML:TaggedValue tag="gentype" value="Java"/>
								<UML:TaggedValue tag="tagged" value="0"/>
								<UML:TaggedValue tag="package_name" value="UC2C.10: Navigate to destination"/>
								<UML:TaggedValue tag="phase" value="1.0"/>
								<UML:TaggedValue tag="author" value="Fabio"/>
								<UML:TaggedValue tag="complexity" value="1"/>
								<UML:TaggedValue tag="status" value="Proposed"/>
								<UML:TaggedValue tag="tpos" value="0"/>
								<UML:TaggedValue tag="ea_localid" value="13889"/>
								<UML:TaggedValue tag="ea_eleType" value="element"/>
								<UML:TaggedValue tag="style" value="BackColor=-1;BorderColor=-1;BorderWidth=-1;FontColor=-1;VSwimLanes=1;HSwimLanes=1;BorderStyle=0;"/>
							</UML:ModelElement.taggedValue>
						</UML:Component>
						<UML:Component xmi.id="EAID_823C668C_7B9E_498f_83CA_11E81881EDF0" visibility="public" namespace="EAPK_6023FBC6_3BDD_4581_9AD7_EB479F476FBB" isRoot="false" isLeaf="false" isAbstract="false">
							<UML:ModelElement.taggedValue>
								<UML:TaggedValue tag="isSpecification" value="false"/>
								<UML:TaggedValue tag="ea_stype" value="Component"/>
								<UML:TaggedValue tag="ea_ntype" value="0"/>
								<UML:TaggedValue tag="version" value="1.0"/>
								<UML:TaggedValue tag="isActive" value="false"/>
								<UML:TaggedValue tag="classifier" value="EAID_1FE721B9_A9E2_47c3_9233_31CED893B264"/>
								<UML:TaggedValue tag="package" value="EAPK_6023FBC6_3BDD_4581_9AD7_EB479F476FBB"/>
								<UML:TaggedValue tag="classname" value="Navigation module"/>
								<UML:TaggedValue tag="date_created" value="2012-05-18 17:05:58"/>
								<UML:TaggedValue tag="date_modified" value="2012-05-18 17:05:58"/>
								<UML:TaggedValue tag="gentype" value="Java"/>
								<UML:TaggedValue tag="tagged" value="0"/>
								<UML:TaggedValue tag="package_name" value="UC2C.10: Navigate to destination"/>
								<UML:TaggedValue tag="phase" value="1.0"/>
								<UML:TaggedValue tag="author" value="Fabio"/>
								<UML:TaggedValue tag="complexity" value="1"/>
								<UML:TaggedValue tag="status" value="Proposed"/>
								<UML:TaggedValue tag="tpos" value="0"/>
								<UML:TaggedValue tag="ea_localid" value="13888"/>
								<UML:TaggedValue tag="ea_eleType" value="element"/>
								<UML:TaggedValue tag="style" value="BackColor=-1;BorderColor=-1;BorderWidth=-1;FontColor=-1;VSwimLanes=1;HSwimLanes=1;BorderStyle=0;"/>
							</UML:ModelElement.taggedValue>
						</UML:Component>
						<UML:Component xmi.id="EAID_840C01B4_2BD9_4605_AE55_E8216334F374" visibility="public" namespace="EAPK_6023FBC6_3BDD_4581_9AD7_EB479F476FBB" isRoot="false" isLeaf="false" isAbstract="false">
							<UML:ModelElement.taggedValue>
								<UML:TaggedValue tag="isSpecification" value="false"/>
								<UML:TaggedValue tag="ea_stype" value="Component"/>
								<UML:TaggedValue tag="ea_ntype" value="0"/>
								<UML:TaggedValue tag="version" value="1.0"/>
								<UML:TaggedValue tag="isActive" value="false"/>
								<UML:TaggedValue tag="classifier" value="EAID_E45F5129_A794_49f2_8FC8_47159EE8C1C4"/>
								<UML:TaggedValue tag="package" value="EAPK_6023FBC6_3BDD_4581_9AD7_EB479F476FBB"/>
								<UML:TaggedValue tag="classname" value="Personal Travel Companion Controller"/>
								<UML:TaggedValue tag="date_created" value="2012-05-18 17:05:51"/>
								<UML:TaggedValue tag="date_modified" value="2012-05-18 17:05:51"/>
								<UML:TaggedValue tag="gentype" value="Java"/>
								<UML:TaggedValue tag="tagged" value="0"/>
								<UML:TaggedValue tag="package_name" value="UC2C.10: Navigate to destination"/>
								<UML:TaggedValue tag="phase" value="1.0"/>
								<UML:TaggedValue tag="author" value="Fabio"/>
								<UML:TaggedValue tag="complexity" value="1"/>
								<UML:TaggedValue tag="status" value="Proposed"/>
								<UML:TaggedValue tag="tpos" value="0"/>
								<UML:TaggedValue tag="ea_localid" value="13887"/>
								<UML:TaggedValue tag="ea_eleType" value="element"/>
								<UML:TaggedValue tag="style" value="BackColor=-1;BorderColor=-1;BorderWidth=-1;FontColor=-1;VSwimLanes=1;HSwimLanes=1;BorderStyle=0;"/>
							</UML:ModelElement.taggedValue>
						</UML:Component>
						<UML:Class xmi.id="EAID_A2033F6A_0EE4_4593_9DA5_C0EABDB0FD9D" visibility="public" namespace="EAPK_6023FBC6_3BDD_4581_9AD7_EB479F476FBB" isRoot="false" isLeaf="false" isAbstract="false">
							<UML:ModelElement.taggedValue>
								<UML:TaggedValue tag="isSpecification" value="false"/>
								<UML:TaggedValue tag="ea_stype" value="InteractionFragment"/>
								<UML:TaggedValue tag="ea_ntype" value="4"/>
								<UML:TaggedValue tag="version" value="1.0"/>
								<UML:TaggedValue tag="isActive" value="false"/>
								<UML:TaggedValue tag="package" value="EAPK_6023FBC6_3BDD_4581_9AD7_EB479F476FBB"/>
								<UML:TaggedValue tag="date_created" value="2012-05-18 17:12:08"/>
								<UML:TaggedValue tag="date_modified" value="2012-05-18 17:12:13"/>
								<UML:TaggedValue tag="gentype" value="&lt;none&gt;"/>
								<UML:TaggedValue tag="tagged" value="0"/>
								<UML:TaggedValue tag="package_name" value="UC2C.10: Navigate to destination"/>
								<UML:TaggedValue tag="phase" value="1.0"/>
								<UML:TaggedValue tag="author" value="Fabio"/>
								<UML:TaggedValue tag="complexity" value="1"/>
								<UML:TaggedValue tag="status" value="Proposed"/>
								<UML:TaggedValue tag="tpos" value="0"/>
								<UML:TaggedValue tag="ea_localid" value="13924"/>
								<UML:TaggedValue tag="ea_eleType" value="element"/>
								<UML:TaggedValue tag="diagram" value="EAID_462B7E9F_9DB8_47b5_9A46_7DA59B6485A4"/>
								<UML:TaggedValue tag="style" value="BackColor=-1;BorderColor=-1;BorderWidth=-1;FontColor=-1;VSwimLanes=1;HSwimLanes=1;BorderStyle=3;"/>
							</UML:ModelElement.taggedValue>
						</UML:Class>
						<UML:Component xmi.id="EAID_CAAA160F_A319_4587_A090_0CD6A814D41A" visibility="public" namespace="EAPK_6023FBC6_3BDD_4581_9AD7_EB479F476FBB" isRoot="false" isLeaf="false" isAbstract="false">
							<UML:ModelElement.taggedValue>
								<UML:TaggedValue tag="isSpecification" value="false"/>
								<UML:TaggedValue tag="ea_stype" value="Component"/>
								<UML:TaggedValue tag="ea_ntype" value="0"/>
								<UML:TaggedValue tag="version" value="1.0"/>
								<UML:TaggedValue tag="isActive" value="false"/>
								<UML:TaggedValue tag="classifier" value="EAID_F70AD162_E134_4b0b_A797_2319F9EA46D7"/>
								<UML:TaggedValue tag="package" value="EAPK_6023FBC6_3BDD_4581_9AD7_EB479F476FBB"/>
								<UML:TaggedValue tag="classname" value="Personal Travel Companion HMI"/>
								<UML:TaggedValue tag="date_created" value="2012-05-18 17:05:46"/>
								<UML:TaggedValue tag="date_modified" value="2012-05-18 17:05:46"/>
								<UML:TaggedValue tag="gentype" value="Java"/>
								<UML:TaggedValue tag="tagged" value="0"/>
								<UML:TaggedValue tag="package_name" value="UC2C.10: Navigate to destination"/>
								<UML:TaggedValue tag="phase" value="1.0"/>
								<UML:TaggedValue tag="author" value="Fabio"/>
								<UML:TaggedValue tag="complexity" value="1"/>
								<UML:TaggedValue tag="status" value="Proposed"/>
								<UML:TaggedValue tag="tpos" value="0"/>
								<UML:TaggedValue tag="ea_localid" value="13886"/>
								<UML:TaggedValue tag="ea_eleType" value="element"/>
								<UML:TaggedValue tag="style" value="BackColor=-1;BorderColor=-1;BorderWidth=-1;FontColor=-1;VSwimLanes=1;HSwimLanes=1;BorderStyle=0;"/>
							</UML:ModelElement.taggedValue>
						</UML:Component>
					</UML:Namespace.ownedElement>
				</UML:Package>
			</UML:Namespace.ownedElement>
		</UML:Model>
		<UML:Diagram name="Navigate to destination" xmi.id="EAID_462B7E9F_9DB8_47b5_9A46_7DA59B6485A4" diagramType="SequenceDiagram" owner="EAPK_6023FBC6_3BDD_4581_9AD7_EB479F476FBB" toolName="Enterprise Architect 2.5">
			<UML:ModelElement.taggedValue>
				<UML:TaggedValue tag="version" value="1.0"/>
				<UML:TaggedValue tag="author" value="Andrea Bragagnini"/>
				<UML:TaggedValue tag="created_date" value="2012-04-16 17:02:09"/>
				<UML:TaggedValue tag="modified_date" value="2012-05-18 17:12:43"/>
				<UML:TaggedValue tag="package" value="EAPK_6023FBC6_3BDD_4581_9AD7_EB479F476FBB"/>
				<UML:TaggedValue tag="type" value="Sequence"/>
				<UML:TaggedValue tag="swimlanes" value="locked=false;orientation=0;width=0;inbar=false;names=false;color=0;bold=false;fcol=0;;cls=0;"/>
				<UML:TaggedValue tag="matrixitems" value="locked=false;matrixactive=false;swimlanesactive=true;width=1;"/>
				<UML:TaggedValue tag="ea_localid" value="1435"/>
				<UML:TaggedValue tag="EAStyle" value="ShowPrivate=1;ShowProtected=1;ShowPublic=1;HideRelationships=0;Locked=0;Border=1;HighlightForeign=1;PackageContents=1;SequenceNotes=0;ScalePrintImage=0;PPgs.cx=2;PPgs.cy=1;DocSize.cx=795;DocSize.cy=1138;ShowDetails=0;Orientation=P;Zoom=100;ShowTags=0;OpParams=1;VisibleAttributeDetail=0;ShowOpRetType=1;ShowIcons=1;CollabNums=0;HideProps=0;ShowReqs=0;ShowCons=0;PaperSize=9;HideParents=0;UseAlias=0;HideAtts=0;HideOps=0;HideStereo=0;HideElemStereo=0;ShowTests=0;ShowMaint=0;ConnectorNotation=UML 2.1;ExplicitNavigability=0;AdvancedElementProps=1;AdvancedFeatureProps=1;AdvancedConnectorProps=1;ShowNotes=0;SuppressBrackets=0;SuppConnectorLabels=0;PrintPageHeadFoot=0;ShowAsList=0;"/>
				<UML:TaggedValue tag="styleex" value="SaveTag=FBD0896A;ExcludeRTF=0;DocAll=0;HideQuals=0;AttPkg=1;ShowTests=0;ShowMaint=0;SuppressFOC=0;INT_ARGS=;INT_RET=;INT_ATT=;SeqTopMargin=50;MatrixActive=0;SwimlanesActive=1;MatrixLineWidth=1;MatrixLocked=0;TConnectorNotation=UML 2.1;TExplicitNavigability=0;AdvancedElementProps=1;AdvancedFeatureProps=1;AdvancedConnectorProps=1;ProfileData=;MDGDgm=;STBLDgm=;ShowNotes=0;VisibleAttributeDetail=0;ShowOpRetType=1;SuppressBrackets=0;SuppConnectorLabels=0;PrintPageHeadFoot=0;ShowAsList=0;"/>
			</UML:ModelElement.taggedValue>
			<UML:Diagram.element>
				<UML:DiagramElement geometry="Left=54;Top=238;Right=1025;Bottom=556;" subject="EAID_A2033F6A_0EE4_4593_9DA5_C0EABDB0FD9D" seqno="1" style="DUID=D7DFB58C;"/>
				<UML:DiagramElement geometry="Left=882;Top=50;Right=1060;Bottom=537;" subject="EAID_BF980BBF_FDCB_4dbc_BB2F_2F838F342E74" seqno="2" style="DUID=5E961A3E;NSL=0;BCol=-1;BFol=-1;LCol=-1;LWth=-1;fontsz=0;bold=0;italic=0;ul=0;charset=0;pitch=0;"/>
				<UML:DiagramElement geometry="Left=724;Top=50;Right=834;Bottom=537;" subject="EAID_2ABA7B39_9B15_4c70_9EFB_614E31549B55" seqno="3" style="DUID=E59A49BC;"/>
				<UML:DiagramElement geometry="Left=561;Top=50;Right=671;Bottom=537;" subject="EAID_823C668C_7B9E_498f_83CA_11E81881EDF0" seqno="4" style="DUID=861A890F;"/>
				<UML:DiagramElement geometry="Left=385;Top=50;Right=495;Bottom=537;" subject="EAID_840C01B4_2BD9_4605_AE55_E8216334F374" seqno="5" style="DUID=000D0F2D;"/>
				<UML:DiagramElement geometry="Left=208;Top=50;Right=318;Bottom=537;" subject="EAID_CAAA160F_A319_4587_A090_0CD6A814D41A" seqno="6" style="DUID=6377B095;"/>
				<UML:DiagramElement geometry="Left=65;Top=50;Right=155;Bottom=537;" subject="EAID_A06BA2A1_6E27_49ba_99C4_9CFE5C2987CF" seqno="7" style="DUID=7B74936A;"/>
				<UML:DiagramElement geometry="SX=0;SY=0;EX=0;EY=0;$LLB=;LLT=;LMT=CX=82:CY=13:OX=0:OY=0:HDN=0:BLD=0:ITA=0:UND=0:CLR=-1:ALN=0:DIR=0:ROT=0;LMB=;LRT=;LRB=;IRHS=;ILHS=;Path=;" subject="EAID_F07C3E81_4C6F_4419_8BB1_BE7014FCBB04" style=";Hidden=0;"/>
				<UML:DiagramElement geometry="SX=0;SY=-13;EX=0;EY=0;$LLB=;LLT=;LMT=CX=82:CY=13:OX=0:OY=0:HDN=0:BLD=0:ITA=0:UND=0:CLR=-1:ALN=0:DIR=0:ROT=0;LMB=;LRT=;LRB=;IRHS=;ILHS=;Path=;" subject="EAID_D8291BFF_C3B2_4c56_8017_CFDC893A838B" style=";Hidden=0;"/>
				<UML:DiagramElement geometry="SX=0;SY=-3;EX=0;EY=0;$LLB=;LLT=;LMT=CX=82:CY=13:OX=0:OY=0:HDN=0:BLD=0:ITA=0:UND=0:CLR=-1:ALN=0:DIR=0:ROT=0;LMB=;LRT=;LRB=;IRHS=;ILHS=;Path=;" subject="EAID_BD45A363_573B_47ba_A91E_33A622825681" style=";Hidden=0;"/>
				<UML:DiagramElement geometry="SX=0;SY=0;EX=0;EY=0;$LLB=;LLT=;LMT=CX=88:CY=13:OX=0:OY=0:HDN=0:BLD=0:ITA=0:UND=0:CLR=-1:ALN=0:DIR=0:ROT=0;LMB=;LRT=;LRB=;IRHS=;ILHS=;Path=;" subject="EAID_F82F4867_6328_4b7d_BAED_81CBD7C2F8DF" style=";Hidden=0;"/>
				<UML:DiagramElement geometry="SX=0;SY=0;EX=0;EY=0;$LLB=;LLT=;LMT=CX=53:CY=13:OX=0:OY=0:HDN=0:BLD=0:ITA=0:UND=0:CLR=-1:ALN=0:DIR=0:ROT=0;LMB=;LRT=;LRB=;IRHS=;ILHS=;Path=;" subject="EAID_FE680E98_6A9A_4207_97FD_5EAAEA0D0264" style=";Hidden=0;"/>
				<UML:DiagramElement geometry="SX=0;SY=-6;EX=0;EY=0;$LLB=;LLT=;LMT=CX=109:CY=13:OX=0:OY=0:HDN=0:BLD=0:ITA=0:UND=0:CLR=-1:ALN=0:DIR=0:ROT=0;LMB=;LRT=;LRB=;IRHS=;ILHS=;Path=;" subject="EAID_4BECD11F_635D_4488_91F7_5FA53180BA4C" style=";Hidden=0;"/>
				<UML:DiagramElement geometry="SX=0;SY=0;EX=0;EY=0;$LLB=;LLT=;LMT=CX=74:CY=13:OX=0:OY=0:HDN=0:BLD=0:ITA=0:UND=0:CLR=-1:ALN=0:DIR=0:ROT=0;LMB=;LRT=;LRB=;IRHS=;ILHS=;Path=;" subject="EAID_18B4F0F7_0C5F_4100_B9FE_339C3F9292F3" style=";Hidden=0;"/>
				<UML:DiagramElement geometry="SX=0;SY=0;EX=0;EY=0;$LLB=;LLT=;LMT=CX=103:CY=13:OX=40:OY=15:HDN=0:BLD=0:ITA=0:UND=0:CLR=-1:ALN=0:DIR=0:ROT=0;LMB=;LRT=;LRB=;IRHS=;ILHS=;Path=;" subject="EAID_C109F109_FA23_481e_AC8A_238D50C46B9D" style=";Hidden=0;"/>
				<UML:DiagramElement geometry="SX=0;SY=0;EX=0;EY=0;$LLB=;LLT=;LMT=CX=96:CY=13:OX=0:OY=0:HDN=0:BLD=0:ITA=0:UND=0:CLR=-1:ALN=0:DIR=0:ROT=0;LMB=;LRT=;LRB=;IRHS=;ILHS=;Path=;" subject="EAID_F6017B6D_F852_47ed_A178_C7803D5094D7" style=";Hidden=0;"/>
				<UML:DiagramElement geometry="SX=0;SY=0;EX=0;EY=0;$LLB=;LLT=;LMT=CX=96:CY=13:OX=0:OY=0:HDN=0:BLD=0:ITA=0:UND=0:CLR=-1:ALN=0:DIR=0:ROT=0;LMB=;LRT=;LRB=;IRHS=;ILHS=;Path=;" subject="EAID_FC85C7DA_091F_43f6_AABB_719D759B100D" style=";Hidden=0;"/>
				<UML:DiagramElement geometry="SX=0;SY=0;EX=0;EY=0;$LLB=;LLT=;LMT=CX=96:CY=13:OX=0:OY=0:HDN=0:BLD=0:ITA=0:UND=0:CLR=-1:ALN=0:DIR=0:ROT=0;LMB=;LRT=;LRB=;IRHS=;ILHS=;Path=;" subject="EAID_3035E43E_4287_4f92_9F61_43A06C521238" style=";Hidden=0;"/>
			</UML:Diagram.element>
		</UML:Diagram>
	</XMI.content>
	<XMI.difference/>
	<XMI.extensions xmi.extender="Enterprise Architect 2.5">
		<EAStub xmi.id="EAPK_BF980BBF_FDCB_4dbc_BB2F_2F838F342E74" name="Multi-Modal Mobility" UMLType="Package"/>
	</XMI.extensions>
</XMI>
